{
  "sessionId": "88de6006-71fe-44be-b362-bc81b8978830",
  "startedAt": "2026-02-24T20:09:29.160Z",
  "mode": "guided",
  "nodeId": "C200",
  "language": "c",
  "masteryState": {
    "byNode": {},
    "history": []
  },
  "misconceptionState": {
    "attempts": [],
    "counts": {}
  },
  "attempts": [],
  "exerciseId": "C200-pointer-depth2",
  "lessonFile": "/Users/noelfelix/Code/oxidized-trombone/.state/workspaces/88de6006_C200/LESSON.md",
  "workspaceDir": "/Users/noelfelix/Code/oxidized-trombone/.state/workspaces/88de6006_C200",
  "attemptState": {
    "exerciseId": "C200-pointer-depth2",
    "attemptIndex": 0,
    "hintLevelUsed": 0,
    "elapsedMinutes": 0,
    "history": [],
    "reviews": []
  },
  "lastHintPack": null,
  "status": "active"
}